inranker/__init__.py
inranker/base.py
inranker/rankers.py
inranker/training/__init__.py
inranker/training/trainer.py
inranker/training/utils.py
inranker-1.1.0.dist-info/LICENSE
inranker-1.1.0.dist-info/METADATA
inranker-1.1.0.dist-info/WHEEL
inranker-1.1.0.dist-info/top_level.txt
inranker-1.1.0.dist-info/RECORD
