Metadata-Version: 2.1
Name: inranker
Version: 1.1.0
Author-email: Thiago Laitz <thiagolaitz@gmail.com>
Requires-Python: >=3.10
License-File: LICENSE
Requires-Dist: accelerate ==0.20.1
Requires-Dist: bitsandbytes ==0.41.1
Requires-Dist: datasets ==2.9.0
Requires-Dist: protobuf ==3.20.1
Requires-Dist: requests ==2.31.0
Requires-Dist: sentencepiece ==0.1.99
Requires-Dist: torch ==2.1.1
Requires-Dist: tqdm ==4.66.1
Requires-Dist: transformers ==4.27.4
